dq_check/__init__.py
dq_check/dq_check.py
dq_check-0.4.1.dist-info/METADATA
dq_check-0.4.1.dist-info/WHEEL
dq_check-0.4.1.dist-info/top_level.txt
dq_check-0.4.1.dist-info/RECORD
