Metadata-Version: 2.1
Name: dq_check
Version: 0.4.1
Summary: A data quality check module for Spark
Author-email: rohan goel <rohan.goel@databricks.com>
Requires-Dist: pyspark
Requires-Dist: pandas
